metadata_client/__init__.py
metadata_client/metadata_client.py
metadata_client/metadata_client_api.py
metadata_client/apis/__init__.py
metadata_client/apis/dark_run_api.py
metadata_client/apis/data_file_api.py
metadata_client/apis/data_group_api.py
metadata_client/apis/data_group_repository_api.py
metadata_client/apis/data_group_type_api.py
metadata_client/apis/data_source_group_api.py
metadata_client/apis/data_source_group_version_api.py
metadata_client/apis/data_type_api.py
metadata_client/apis/experiment_api.py
metadata_client/apis/experiment_type_api.py
metadata_client/apis/instrument_api.py
metadata_client/apis/instrument_cycle_api.py
metadata_client/apis/parameter_api.py
metadata_client/apis/parameter_type_api.py
metadata_client/apis/proposal_api.py
metadata_client/apis/proposal_technique_api.py
metadata_client/apis/report_api.py
metadata_client/apis/repostory_api.py
metadata_client/apis/run_api.py
metadata_client/apis/sample_api.py
metadata_client/apis/technique_api.py
metadata_client/apis/unit_api.py
metadata_client/apis/user_api.py
metadata_client/common/__init__.py
metadata_client/common/base.py
metadata_client/common/config.py
metadata_client/common/util.py
metadata_client/modules/__init__.py
metadata_client/modules/dark_run.py
metadata_client/modules/data_file.py
metadata_client/modules/data_group.py
metadata_client/modules/data_group_repository.py
metadata_client/modules/data_group_type.py
metadata_client/modules/data_source_group.py
metadata_client/modules/data_source_group_version.py
metadata_client/modules/data_type.py
metadata_client/modules/experiment.py
metadata_client/modules/experiment_type.py
metadata_client/modules/instrument.py
metadata_client/modules/instrument_cycle.py
metadata_client/modules/parameter.py
metadata_client/modules/parameter_type.py
metadata_client/modules/proposal.py
metadata_client/modules/proposal_technique.py
metadata_client/modules/report.py
metadata_client/modules/repository.py
metadata_client/modules/run.py
metadata_client-4.1.2.dist-info/licenses/AUTHORS.rst
metadata_client-4.1.2.dist-info/licenses/LICENSE
metadata_client-4.1.2.dist-info/METADATA
metadata_client-4.1.2.dist-info/WHEEL
metadata_client-4.1.2.dist-info/top_level.txt
metadata_client-4.1.2.dist-info/RECORD
