Metadata-Version: 2.4
Name: metadata_client
Version: 4.1.2
Summary: Python Client for European XFEL Metadata Catalogue Web App available at https://in.xfel.eu/metadata
Home-page: https://git.xfel.eu/ITDM/metadata_client
Author: Luís Maia
Author-email: luis.maia@xfel.eu
Maintainer: Luís Maia
Maintainer-email: luis.maia@xfel.eu
License: MIT
Platform: any
Classifier: Development Status :: 5 - Production/Stable
Classifier: Environment :: Web Environment
Classifier: Environment :: Console
Classifier: Intended Audience :: Developers
Classifier: Intended Audience :: Science/Research
Classifier: Natural Language :: English
Classifier: License :: OSI Approved :: MIT License
Classifier: Programming Language :: Python
Classifier: Programming Language :: Python :: 3
Classifier: Operating System :: OS Independent
Classifier: Topic :: Scientific/Engineering :: Information Analysis
Classifier: Topic :: Software Development :: Libraries :: Python Modules
Requires-Python: >=3.7
License-File: LICENSE
License-File: AUTHORS.rst
Requires-Dist: oauthlib
Requires-Dist: requests<2.30
Requires-Dist: requests-oauthlib
Requires-Dist: oauth2_xfel_client>=6.1
Requires-Dist: pytz
Provides-Extra: test
Requires-Dist: pytest; extra == "test"
Requires-Dist: flaky; extra == "test"
Requires-Dist: pytest-cov; extra == "test"
Requires-Dist: python-dateutil; extra == "test"
Requires-Dist: pytz; extra == "test"
Requires-Dist: pycodestyle; extra == "test"
Requires-Dist: setuptools; extra == "test"
Dynamic: author
Dynamic: author-email
Dynamic: classifier
Dynamic: description
Dynamic: home-page
Dynamic: license
Dynamic: license-file
Dynamic: maintainer
Dynamic: maintainer-email
Dynamic: platform
Dynamic: provides-extra
Dynamic: requires-dist
Dynamic: requires-python
Dynamic: summary
